Rythmix_dot_py/__init__.py
Rythmix_dot_py/install_vlc.py
Rythmix_dot_py/main.py
Rythmix_dot_py-1.0.6.dist-info/METADATA
Rythmix_dot_py-1.0.6.dist-info/WHEEL
Rythmix_dot_py-1.0.6.dist-info/entry_points.txt
Rythmix_dot_py-1.0.6.dist-info/top_level.txt
Rythmix_dot_py-1.0.6.dist-info/RECORD
