Metadata-Version: 2.1
Name: Rythmix-dot-py
Version: 1.0.6
Summary: A simple CLI tool for playing music. (VLC is required!)
Requires-Dist: youtube-search-python ==1.6.6
Requires-Dist: yt-dlp ==2024.7.25
Requires-Dist: python-vlc ==3.0.20123
Requires-Dist: distro ==1.9.0
